odoo10_addon_base_delivery_carrier_files_document-10.0.1.0.1-py3.8-nspkg.pth
odoo/addons/base_delivery_carrier_files_document/README.rst
odoo/addons/base_delivery_carrier_files_document/__init__.py
odoo/addons/base_delivery_carrier_files_document/__manifest__.py
odoo/addons/base_delivery_carrier_files_document/demo/carrier_file_demo.xml
odoo/addons/base_delivery_carrier_files_document/i18n/base_delivery_carrier_files_document.pot
odoo/addons/base_delivery_carrier_files_document/i18n/de.po
odoo/addons/base_delivery_carrier_files_document/i18n/fr.po
odoo/addons/base_delivery_carrier_files_document/models/__init__.py
odoo/addons/base_delivery_carrier_files_document/models/delivery_carrier_file.py
odoo/addons/base_delivery_carrier_files_document/readme/CONTRIBUTORS.rst
odoo/addons/base_delivery_carrier_files_document/readme/DESCRIPTION.rst
odoo/addons/base_delivery_carrier_files_document/static/description/icon.png
odoo/addons/base_delivery_carrier_files_document/static/description/index.html
odoo/addons/base_delivery_carrier_files_document/tests/__init__.py
odoo/addons/base_delivery_carrier_files_document/tests/test_base_delivery_carrier_files_document.py
odoo10_addon_base_delivery_carrier_files_document-10.0.1.0.1.dist-info/METADATA
odoo10_addon_base_delivery_carrier_files_document-10.0.1.0.1.dist-info/WHEEL
odoo10_addon_base_delivery_carrier_files_document-10.0.1.0.1.dist-info/namespace_packages.txt
odoo10_addon_base_delivery_carrier_files_document-10.0.1.0.1.dist-info/top_level.txt
odoo10_addon_base_delivery_carrier_files_document-10.0.1.0.1.dist-info/RECORD
