Metadata-Version: 2.1
Name: odoo10-addon-base-delivery-carrier-files-document
Version: 10.0.1.0.1
Summary: Allow to store carrier files as attachments. Auto-install when the module Document and Base Delivery Carrier Files are installed.
Home-page: http://www.camptocamp.com
Author: Camptocamp,Odoo Community Association (OCA)
Author-email: support@odoo-community.org
License: AGPL-3
Platform: UNKNOWN
Classifier: Programming Language :: Python
Classifier: Framework :: Odoo
Classifier: License :: OSI Approved :: GNU Affero General Public License v3
Requires-Python: ~=2.7
Requires-Dist: odoo10-addon-base-delivery-carrier-files
Requires-Dist: odoo (<10.1dev,>=10.0)
